devai/__init__.py
devai/activation_funcs.py
devai/basics.py
devai/callbacks.py
devai/dataloaders.py
devai/eda.py
devai/evaluation.py
devai/hooks.py
devai/loss_funcs.py
devai/maps.py
devai/metrics.py
devai/model.py
devai/optimizers.py
devai/text.py
devai/scripts/__init__.py
devai/scripts/image_split_half.py
devai/scripts/lnk2alias.py
devai/scripts/notebook2script.py
devai/scripts/read_frames_fast.py
devai/scripts/text_replacer_ipynb.py
devai/scripts/update_sqlite.py
devai/scripts/vid2frames.py
devai/scripts/video_cropper.py
devai/utils/__init__.py
devai/utils/ml.py
devai-0.0a8.dist-info/METADATA
devai-0.0a8.dist-info/WHEEL
devai-0.0a8.dist-info/top_level.txt
devai-0.0a8.dist-info/RECORD
