Metadata-Version: 2.1
Name: devai
Version: 0.0a8
Summary: UNKNOWN
Home-page: https://github.com/devkosal/devai
Author: Dev Sharma
Author-email: dev.sharma@columbia.edu
License: MIT
Platform: UNKNOWN
Classifier: Programming Language :: Python :: 3
Classifier: License :: OSI Approved :: MIT License
Classifier: Operating System :: OS Independent
Requires-Python: >=3.6
